polars_credit-0.5.0.dist-info/METADATA
polars_credit-0.5.0.dist-info/WHEEL
polars_credit-0.5.0.dist-info/licenses/LICENSE
polars_credit/eda.py
polars_credit/bin.py
polars_credit/feature_selection.py
polars_credit/__init__.py
polars_credit/base.py
polars_credit/util.py
polars_credit/impute.py
polars_credit/woe.py
polars_credit/_internal.abi3.so
polars_credit-0.5.0.dist-info/RECORD
